CHANGES.txt
LICENSE.txt
MANIFEST.in
README.rst
setup.py
js_project/__init__.py
js_project.egg-info/PKG-INFO
js_project.egg-info/SOURCES.txt
js_project.egg-info/dependency_links.txt
js_project.egg-info/entry_points.txt
js_project.egg-info/requires.txt
js_project.egg-info/top_level.txt
js_project/scaffolds/__init__.py
js_project/scaffolds/js_project_scaffold/CHANGES.txt_tmpl
js_project/scaffolds/js_project_scaffold/MANIFEST.in_tmpl
js_project/scaffolds/js_project_scaffold/README.md_tmpl
js_project/scaffolds/js_project_scaffold/README.rst_tmpl
js_project/scaffolds/js_project_scaffold/setup.py_tmpl
js_project/scaffolds/js_project_scaffold/js/__init__.py
js_project/scaffolds/js_project_scaffold/js/+package+/__init__.py_tmpl
js_project/scaffolds/js_project_scaffold/js/+package+/resources/+package+.css
js_project/scaffolds/js_project_scaffold/js/+package+/resources/+package+.js