Metadata-Version: 1.0
Name: js-project
Version: 0.1.4
Summary: pcreate scaffold for fanstatic resource library projects
Home-page: https://github.com/ppinette/pyramid_foundation
Author: Parker Pinette
Author-email: parker@parkerpinette.com
License: LICENSE.txt
Platform: UNKNOWN
